pp_heig_plot.py
pp_heig_signal.py
pp_heig_simulation.py
pandapower_heig_ui-0.8.1.dist-info/LICENSE
pandapower_heig_ui-0.8.1.dist-info/METADATA
pandapower_heig_ui-0.8.1.dist-info/WHEEL
pandapower_heig_ui-0.8.1.dist-info/top_level.txt
pandapower_heig_ui-0.8.1.dist-info/RECORD
