Metadata-Version: 2.1
Name: pandapower-heig-ui
Version: 0.8.1
Summary: A set of function coded in order to help heig-vd students to use pandapower library.
Author: Luca Tomasini
Classifier: Programming Language :: Python :: 3
Classifier: License :: OSI Approved :: MIT License
Classifier: Operating System :: OS Independent
Requires-Python: >=3.10
License-File: LICENSE
